poml/__init__.py
poml/__main__.py
poml/_tags.py
poml/_version.py
poml/api.py
poml/cli.py
poml/prompt.py
poml/js/.gitignore
poml/js/cli.js
poml/node_modules/@img/sharp-darwin-arm64/LICENSE
poml/node_modules/@img/sharp-darwin-arm64/README.md
poml/node_modules/@img/sharp-darwin-arm64/package.json
poml/node_modules/@img/sharp-darwin-arm64/lib/sharp-darwin-arm64.node
poml/node_modules/@img/sharp-libvips-darwin-arm64/README.md
poml/node_modules/@img/sharp-libvips-darwin-arm64/package.json
poml/node_modules/@img/sharp-libvips-darwin-arm64/versions.json
poml/node_modules/@img/sharp-libvips-darwin-arm64/lib/index.js
poml/node_modules/@img/sharp-libvips-darwin-arm64/lib/libvips-cpp.42.dylib
poml/node_modules/@img/sharp-libvips-darwin-arm64/lib/glib-2.0/include/glibconfig.h
poml/node_modules/color/LICENSE
poml/node_modules/color/README.md
poml/node_modules/color/index.js
poml/node_modules/color/package.json
poml/node_modules/color-convert/CHANGELOG.md
poml/node_modules/color-convert/LICENSE
poml/node_modules/color-convert/README.md
poml/node_modules/color-convert/conversions.js
poml/node_modules/color-convert/index.js
poml/node_modules/color-convert/package.json
poml/node_modules/color-convert/route.js
poml/node_modules/color-name/LICENSE
poml/node_modules/color-name/README.md
poml/node_modules/color-name/index.js
poml/node_modules/color-name/package.json
poml/node_modules/color-string/LICENSE
poml/node_modules/color-string/README.md
poml/node_modules/color-string/index.js
poml/node_modules/color-string/package.json
poml/node_modules/detect-libc/LICENSE
poml/node_modules/detect-libc/README.md
poml/node_modules/detect-libc/index.d.ts
poml/node_modules/detect-libc/package.json
poml/node_modules/detect-libc/lib/detect-libc.js
poml/node_modules/detect-libc/lib/filesystem.js
poml/node_modules/detect-libc/lib/process.js
poml/node_modules/is-arrayish/LICENSE
poml/node_modules/is-arrayish/README.md
poml/node_modules/is-arrayish/index.js
poml/node_modules/is-arrayish/package.json
poml-0.0.7.dist-info/METADATA
poml-0.0.7.dist-info/WHEEL
poml-0.0.7.dist-info/entry_points.txt
poml-0.0.7.dist-info/licenses/LICENSE
poml-0.0.7.dist-info/RECORD
