Metadata-Version: 2.4
Name: poml
Version: 0.0.7
Summary: Prompt Orchestration Markup Language
License: The MIT License (MIT)
License-File: LICENSE
Requires-Python: >=3.9
Requires-Dist: nodejs-wheel
Provides-Extra: dev
Requires-Dist: black; extra == 'dev'
Requires-Dist: flake8; extra == 'dev'
Requires-Dist: hatch; extra == 'dev'
Requires-Dist: pytest; extra == 'dev'
